payments/__init__.py
payments/core.py
payments/fields.py
payments/forms.py
payments/models.py
payments/signals.py
payments/test_core.py
payments/urls.py
payments/utils.py
payments/widgets.py
payments/authorizenet/__init__.py
payments/authorizenet/forms.py
payments/authorizenet/test_authorizenet.py
payments/braintree/__init__.py
payments/braintree/forms.py
payments/braintree/test_braintree.py
payments/coinbase/__init__.py
payments/coinbase/test_coinbase.py
payments/cybersource/__init__.py
payments/cybersource/forms.py
payments/cybersource/test_cybersource.py
payments/dotpay/__init__.py
payments/dotpay/forms.py
payments/dotpay/test_dotpay.py
payments/dummy/__init__.py
payments/dummy/forms.py
payments/dummy/test_dummy.py
payments/paygate/__init__.py
payments/paygate/utils.py
payments/paypal/__init__.py
payments/paypal/forms.py
payments/paypal/test_paypal.py
payments/sagepay/__init__.py
payments/sagepay/test_sagepay.py
payments/sofort/__init__.py
payments/sofort/test_sofort.py
payments/stripe/__init__.py
payments/stripe/forms.py
payments/stripe/test_stripe.py
payments/stripe/widgets.py
payments/wallet/__init__.py
payments/wallet/forms.py
payments/wallet/test_wallet.py
payments/wallet/widgets.py
payments_paygate-0.11.0.3.dist-info/DESCRIPTION.rst
payments_paygate-0.11.0.3.dist-info/METADATA
payments_paygate-0.11.0.3.dist-info/RECORD
payments_paygate-0.11.0.3.dist-info/WHEEL
payments_paygate-0.11.0.3.dist-info/metadata.json
payments_paygate-0.11.0.3.dist-info/top_level.txt
