Metadata-Version: 2.0
Name: payments-paygate
Version: 0.11.0.3
Summary: Universal payment handling for Django
Home-page: https://github.com/oosthuizenb/payments-paygate
Author: oosthuizenb
Author-email: hello@mirumee.com
License: UNKNOWN
Platform: UNKNOWN
Classifier: Environment :: Web Environment
Classifier: Intended Audience :: Developers
Classifier: License :: OSI Approved :: BSD License
Classifier: Operating System :: OS Independent
Classifier: Programming Language :: Python
Classifier: Programming Language :: Python :: 2.7
Classifier: Programming Language :: Python :: 3.4
Classifier: Programming Language :: Python :: 3.5
Classifier: Framework :: Django
Classifier: Topic :: Software Development :: Libraries :: Application Frameworks
Classifier: Topic :: Software Development :: Libraries :: Python Modules
Requires-Dist: Django (>=1.5)
Requires-Dist: PyJWT (>=1.3.0)
Requires-Dist: braintree (>=3.14.0)
Requires-Dist: cryptography (>=1.1.0)
Requires-Dist: requests (>=1.2.0)
Requires-Dist: stripe (>=1.9.8)
Requires-Dist: suds-jurko (>=0.6)
Requires-Dist: xmltodict (>=0.9.2)
